LICENSE
MANIFEST.in
README.rst
flask_jsonschema.py
setup.py
tests.py
Flask_JsonSchema.egg-info/PKG-INFO
Flask_JsonSchema.egg-info/SOURCES.txt
Flask_JsonSchema.egg-info/dependency_links.txt
Flask_JsonSchema.egg-info/not-zip-safe
Flask_JsonSchema.egg-info/requires.txt
Flask_JsonSchema.egg-info/top_level.txt